haystack_entailment_checker/__init__.py
haystack_entailment_checker/entailment_checker.py
haystack_entailment_checker-0.0.4.dist-info/METADATA
haystack_entailment_checker-0.0.4.dist-info/WHEEL
haystack_entailment_checker-0.0.4.dist-info/RECORD
